foxnose_sdk/__init__.py
foxnose_sdk/config.py
foxnose_sdk/errors.py
foxnose_sdk/http.py
foxnose_sdk/auth/__init__.py
foxnose_sdk/auth/base.py
foxnose_sdk/auth/jwt.py
foxnose_sdk/auth/secure.py
foxnose_sdk/flux/__init__.py
foxnose_sdk/flux/client.py
foxnose_sdk/management/__init__.py
foxnose_sdk/management/client.py
foxnose_sdk/management/models.py
foxnose_sdk-0.1.0.dist-info/METADATA
foxnose_sdk-0.1.0.dist-info/WHEEL
foxnose_sdk-0.1.0.dist-info/licenses/LICENSE
foxnose_sdk-0.1.0.dist-info/RECORD
