Metadata-Version: 2.4
Name: foxnose-sdk
Version: 0.1.0
Summary: Official Python client for FoxNose Management and Flux APIs
Project-URL: Homepage, https://foxnose.net
Project-URL: Source, https://github.com/FoxNoseTech/foxnose-python
Project-URL: Documentation, https://docs.foxnose.net
Author: FoxNose
License: Apache-2.0
License-File: LICENSE
Keywords: ai,api,embeddings,foxnose,knowledge-base,rag,sdk
Classifier: Development Status :: 4 - Beta
Classifier: Intended Audience :: Developers
Classifier: License :: OSI Approved :: Apache Software License
Classifier: Operating System :: OS Independent
Classifier: Programming Language :: Python :: 3
Classifier: Programming Language :: Python :: 3.9
Classifier: Programming Language :: Python :: 3.10
Classifier: Programming Language :: Python :: 3.11
Classifier: Programming Language :: Python :: 3.12
Classifier: Topic :: Software Development :: Libraries :: Python Modules
Classifier: Typing :: Typed
Requires-Python: >=3.9
Requires-Dist: cryptography>=42.0.0
Requires-Dist: httpx>=0.27.0
Requires-Dist: pydantic>=2.6
Requires-Dist: typing-extensions>=4.8
Provides-Extra: docs
Requires-Dist: mkdocs-material>=9.5; extra == 'docs'
Requires-Dist: mkdocs>=1.6; extra == 'docs'
Requires-Dist: mkdocstrings[python]>=0.24; extra == 'docs'
Provides-Extra: test
Requires-Dist: pytest-asyncio>=0.23; extra == 'test'
Requires-Dist: pytest-cov>=4.1; extra == 'test'
Requires-Dist: pytest>=8.2; extra == 'test'
